src/__init__.py
src/exception/__init__.py
src/exception/exception.py
src/logging/__init__.py
src/logging/logger.py
src/pipelines/ETLpipeline.py
src/pipelines/Trainpipeline.py
src/pipelines/__init__.py
src/pipelines/pipeline.py
src/scripts/__init__.py
src/scripts/push_data.py
src/utils/__init__.py
src/utils/utils.py
aqi_prediction_sg-0.0.1.dist-info/METADATA
aqi_prediction_sg-0.0.1.dist-info/WHEEL
aqi_prediction_sg-0.0.1.dist-info/top_level.txt
aqi_prediction_sg-0.0.1.dist-info/RECORD
