Metadata-Version: 2.4
Name: aqi-prediction-sg
Version: 0.0.1
Summary: AQI Prediction using CatBoost and Flask
Author: Shivam Gupta
Author-email: sg4781778@gmail.com
Requires-Python: >=3.11
Dynamic: author
Dynamic: author-email
Dynamic: requires-python
Dynamic: summary
